{
  "project_info": {
    "project_number": "633808468002",
    "firebase_url": "https://testpj-4e0fc-default-rtdb.asia-southeast1.firebasedatabase.app",
    "project_id": "testpj-4e0fc",
    "storage_bucket": "testpj-4e0fc.appspot.com"
  },
  "client": [
    {
      "client_info": {
        "mobilesdk_app_id": "1:633808468002:android:9b839e353b1a3f5d8bf27b",
        "android_client_info": {
          "package_name": "com.example.pbl_55"
        }
      },
      "oauth_client": [
        {
          "client_id": "633808468002-440lqkgok2ivdj5jp25hc7buj5ael5mb.apps.googleusercontent.com",
          "client_type": 3
        }
      ],
      "api_key": [
        {
          "current_key": "AIzaSyASeiAUXSDs-DUvSGRTUbfx-Tu86J7DMrY"
        }
      ],
      "services": {
        "appinvite_service": {
          "other_platform_oauth_client": [
            {
              "client_id": "633808468002-440lqkgok2ivdj5jp25hc7buj5ael5mb.apps.googleusercontent.com",
              "client_type": 3
            }
          ]
        }
      }
    },
    {
      "client_info": {
        "mobilesdk_app_id": "1:633808468002:android:f1869d1be4f007938bf27b",
        "android_client_info": {
          "package_name": "com.midterm.pbl5"
        }
      },
      "oauth_client": [
        {
          "client_id": "633808468002-440lqkgok2ivdj5jp25hc7buj5ael5mb.apps.googleusercontent.com",
          "client_type": 3
        }
      ],
      "api_key": [
        {
          "current_key": "AIzaSyASeiAUXSDs-DUvSGRTUbfx-Tu86J7DMrY"
        }
      ],
      "services": {
        "appinvite_service": {
          "other_platform_oauth_client": [
            {
              "client_id": "633808468002-440lqkgok2ivdj5jp25hc7buj5ael5mb.apps.googleusercontent.com",
              "client_type": 3
            }
          ]
        }
      }
    },
    {
      "client_info": {
        "mobilesdk_app_id": "1:633808468002:android:a4ab1d7a6fcf28e48bf27b",
        "android_client_info": {
          "package_name": "com.niranjan.maps"
        }
      },
      "oauth_client": [
        {
          "client_id": "633808468002-440lqkgok2ivdj5jp25hc7buj5ael5mb.apps.googleusercontent.com",
          "client_type": 3
        }
      ],
      "api_key": [
        {
          "current_key": "AIzaSyASeiAUXSDs-DUvSGRTUbfx-Tu86J7DMrY"
        }
      ],
      "services": {
        "appinvite_service": {
          "other_platform_oauth_client": [
            {
              "client_id": "633808468002-440lqkgok2ivdj5jp25hc7buj5ael5mb.apps.googleusercontent.com",
              "client_type": 3
            }
          ]
        }
      }
    }
  ],
  "configuration_version": "1"
}